robotmcp/__init__.py
robotmcp/server.py
robotmcp/attach/__init__.py
robotmcp/attach/mcp_attach.py
robotmcp/components/__init__.py
robotmcp/components/keyword_matcher.py
robotmcp/components/library_recommender.py
robotmcp/components/nlp_processor.py
robotmcp/components/state_manager.py
robotmcp/components/test_builder.py
robotmcp/components/browser/__init__.py
robotmcp/components/browser/browser_library_manager.py
robotmcp/components/execution/__init__.py
robotmcp/components/execution/execution_coordinator.py
robotmcp/components/execution/external_rf_client.py
robotmcp/components/execution/keyword_executor.py
robotmcp/components/execution/locator_converter.py
robotmcp/components/execution/mobile_capability_service.py
robotmcp/components/execution/page_source_service.py
robotmcp/components/execution/rf_native_context_manager.py
robotmcp/components/execution/session_manager.py
robotmcp/components/execution/suite_execution_service.py
robotmcp/components/variables/__init__.py
robotmcp/components/variables/variable_resolver.py
robotmcp/config/__init__.py
robotmcp/config/library_registry.py
robotmcp/core/__init__.py
robotmcp/core/dynamic_keyword_orchestrator.py
robotmcp/core/event_bus.py
robotmcp/core/keyword_discovery.py
robotmcp/core/library_manager.py
robotmcp/core/session_manager.py
robotmcp/frontend/__init__.py
robotmcp/frontend/api.py
robotmcp/frontend/apps.py
robotmcp/frontend/asgi.py
robotmcp/frontend/bridge.py
robotmcp/frontend/config.py
robotmcp/frontend/controller.py
robotmcp/frontend/devserver.py
robotmcp/frontend/django_app.py
robotmcp/frontend/urls.py
robotmcp/frontend/views.py
robotmcp/frontend/static/frontend/app.js
robotmcp/frontend/static/frontend/base.css
robotmcp/frontend/templates/frontend/index.html
robotmcp/frontend/templates/frontend/layout.html
robotmcp/models/__init__.py
robotmcp/models/browser_models.py
robotmcp/models/config_models.py
robotmcp/models/execution_models.py
robotmcp/models/library_models.py
robotmcp/models/session_models.py
rf_mcp-0.27.0.dist-info/METADATA
rf_mcp-0.27.0.dist-info/WHEEL
rf_mcp-0.27.0.dist-info/entry_points.txt
rf_mcp-0.27.0.dist-info/licenses/LICENSE
rf_mcp-0.27.0.dist-info/RECORD
