Metadata-Version: 2.4
Name: rf-mcp
Version: 0.27.0
Summary: Robot Framework MCP Server - Natural Language Test Automation Bridge
Project-URL: Homepage, https://github.com/manykarim/rf-mcp
Project-URL: Repository, https://github.com/manykarim/rf-mcp
Project-URL: Bug Tracker, https://github.com/manykarim/rf-mcp/issues
Project-URL: Documentation, https://github.com/manykarim/rf-mcp#readme
Author: Many Kasiriha
License: Apache-2.0
License-File: LICENSE
Requires-Python: >=3.10
Requires-Dist: beautifulsoup4>=4.11.0
Requires-Dist: fastmcp>=2.0.0
Requires-Dist: lxml>=4.9.0
Requires-Dist: pydantic>=2.0.0
Requires-Dist: python-dotenv>=1.0.1
Requires-Dist: pyyaml>=6.0.0
Requires-Dist: robotframework>=7.0
Provides-Extra: all
Requires-Dist: django<5.0,>=4.2; extra == 'all'
Requires-Dist: robotframework-appiumlibrary; extra == 'all'
Requires-Dist: robotframework-browser; extra == 'all'
Requires-Dist: robotframework-databaselibrary; extra == 'all'
Requires-Dist: robotframework-requests; extra == 'all'
Requires-Dist: robotframework-seleniumlibrary; extra == 'all'
Requires-Dist: uvicorn[standard]>=0.24; extra == 'all'
Provides-Extra: api
Requires-Dist: robotframework-requests; extra == 'api'
Provides-Extra: database
Requires-Dist: robotframework-databaselibrary; extra == 'database'
Provides-Extra: dev
Requires-Dist: black>=22.0.0; extra == 'dev'
Requires-Dist: coverage[toml]>=7.6.0; extra == 'dev'
Requires-Dist: invoke>=2.2.0; extra == 'dev'
Requires-Dist: mypy>=1.0.0; extra == 'dev'
Requires-Dist: openai>=1.51.0; extra == 'dev'
Requires-Dist: pre-commit>=2.20.0; extra == 'dev'
Requires-Dist: pydantic-ai>=1.37.0; extra == 'dev'
Requires-Dist: pytest-asyncio>=0.21.0; extra == 'dev'
Requires-Dist: pytest>=7.0.0; extra == 'dev'
Requires-Dist: python-dotenv>=1.0.1; extra == 'dev'
Provides-Extra: frontend
Requires-Dist: django<5.0,>=4.2; extra == 'frontend'
Requires-Dist: uvicorn[standard]>=0.24; extra == 'frontend'
Provides-Extra: mobile
Requires-Dist: robotframework-appiumlibrary; extra == 'mobile'
Provides-Extra: slim
Provides-Extra: web
Requires-Dist: robotframework-browser; extra == 'web'
Requires-Dist: robotframework-seleniumlibrary; extra == 'web'
